jd_wechatpay/__init__.py
jd_wechatpay/apply4subject.py
jd_wechatpay/applyment.py
jd_wechatpay/businesscircle.py
jd_wechatpay/capital.py
jd_wechatpay/complaint.py
jd_wechatpay/core.py
jd_wechatpay/gold_plan.py
jd_wechatpay/invoice.py
jd_wechatpay/marketing.py
jd_wechatpay/mch.py
jd_wechatpay/media.py
jd_wechatpay/merchant_risk.py
jd_wechatpay/parking.py
jd_wechatpay/payscore.py
jd_wechatpay/profitsharing.py
jd_wechatpay/smartguide.py
jd_wechatpay/transaction.py
jd_wechatpay/transfer.py
jd_wechatpay/type.py
jd_wechatpay/utils.py
jd_wechatpay-0.1.1.dist-info/LICENSE
jd_wechatpay-0.1.1.dist-info/METADATA
jd_wechatpay-0.1.1.dist-info/WHEEL
jd_wechatpay-0.1.1.dist-info/top_level.txt
jd_wechatpay-0.1.1.dist-info/RECORD
