Metadata-Version: 2.1
Name: jd-wechatpay
Version: 0.1.1
Summary: Wechat pay v3 python sdk, by JD
Author-email: wxg001 <wxg001@21cn.com>
License: MIT
Project-URL: Homepage, https://pypi.org/project/jd-wechatpay/
Project-URL: Bug Tracker, https://pypi.org/project/jd-wechatpay/
Classifier: Programming Language :: Python :: 3.7
Classifier: Programming Language :: Python :: 3.8
Classifier: Programming Language :: Python :: 3.9
Classifier: Programming Language :: Python :: 3.10
Classifier: License :: OSI Approved :: MIT License
Classifier: Operating System :: OS Independent
Requires-Python: >=3.7
License-File: LICENSE
Requires-Dist: Cryptography
Requires-Dist: requests
